marktripy/__init__.py
marktripy/_version.py
marktripy/core/__init__.py
marktripy/core/ast.py
marktripy/core/parser.py
marktripy/core/validator.py
marktripy/extensions/__init__.py
marktripy/extensions/base.py
marktripy/extensions/gfm.py
marktripy/extensions/kbd.py
marktripy/extensions/strikethrough.py
marktripy/extensions/tasklist.py
marktripy/parsers/__init__.py
marktripy/parsers/markdown_it.py
marktripy/parsers/mistletoe_parser.py
marktripy/renderers/__init__.py
marktripy/renderers/base.py
marktripy/renderers/html.py
marktripy/renderers/markdown.py
marktripy/transformers/__init__.py
marktripy/transformers/base.py
marktripy/transformers/heading.py
marktripy/transformers/id_generator.py
marktripy/transformers/link_reference.py
marktripy/transformers/toc.py
marktripy/utils/__init__.py
marktripy/utils/slugify.py
marktripy-1.0.3.dist-info/METADATA
marktripy-1.0.3.dist-info/WHEEL
marktripy-1.0.3.dist-info/entry_points.txt
marktripy-1.0.3.dist-info/RECORD
