Metadata-Version: 2.4
Name: marktripy
Version: 1.0.3
Summary: A Python package for converting Markdown to AST and back to Markdown
Project-URL: Homepage, https://github.com/twardoch/marktripy
Project-URL: Repository, https://github.com/twardoch/marktripy
Project-URL: Issues, https://github.com/twardoch/marktripy/issues
Author-email: Adam <adam@example.com>
License: MIT
Keywords: ast,commonmark,converter,markdown,parser
Classifier: Development Status :: 3 - Alpha
Classifier: Intended Audience :: Developers
Classifier: Programming Language :: Python :: 3
Classifier: Programming Language :: Python :: 3.12
Classifier: Topic :: Software Development :: Libraries :: Python Modules
Classifier: Topic :: Text Processing :: Markup
Requires-Python: >=3.12
Requires-Dist: fire>=0.7.0
Requires-Dist: loguru>=0.7.3
Requires-Dist: markdown-it-py[linkify,plugins]>=3.0.0
Requires-Dist: mistletoe>=1.4.0
Requires-Dist: rich>=14.1.0
